simple_distance_calculator
tests
