Metadata-Version: 2.1
Name: simple-distance-calculator
Version: 0.0.2
Summary: A distance calculator
Home-page: https://github.com/Aivcho/distance_calculator
Author: Aivcho
Author-email: achomskis@gmail.com
License: MIT
Classifier: Programming Language :: Python :: 3
Classifier: License :: OSI Approved :: MIT License
Classifier: Operating System :: OS Independent
License-File: LICENSE.txt
